README.rst
setup.cfg
setup.py
TTASSL/__init__.py
TTASSL/semiSupervised.py
TTASSL/utils.py
TTASSL.egg-info/PKG-INFO
TTASSL.egg-info/SOURCES.txt
TTASSL.egg-info/dependency_links.txt
TTASSL.egg-info/requires.txt
TTASSL.egg-info/top_level.txt